wa_ssh
